bumbo/__init__.py
bumbo/api.py
bumbo/middleware.py
bumbo/response.py
bumbo_yuzhanhuang1119-0.0.4.dist-info/METADATA
bumbo_yuzhanhuang1119-0.0.4.dist-info/WHEEL
bumbo_yuzhanhuang1119-0.0.4.dist-info/top_level.txt
bumbo_yuzhanhuang1119-0.0.4.dist-info/RECORD
